idk.cpython-39-x86_64-linux-gnu.so
wolframalph_idk-1.0.dist-info/top_level.txt
wolframalph_idk-1.0.dist-info/RECORD
wolframalph_idk-1.0.dist-info/WHEEL
wolframalph_idk-1.0.dist-info/METADATA
